{
  "consumed_at_utc": "2026-06-02T15:14:47+00:00",
  "expires_at_utc": "2026-06-02T15:15:47+00:00",
  "issued_at_utc": "2026-06-02T15:14:47+00:00",
  "payload": {
    "blockers": [],
    "created_at_utc": "2026-06-02T15:14:47+00:00",
    "draft_id": "11ff617a-bc8b-4456-be54-61dd21d3909d",
    "expires_at_utc": "2026-06-02T15:29:47+00:00",
    "instrument": "INTC",
    "limit_price": 23.64,
    "max_notional_eur": 47.28,
    "order_type": "LIMIT_BUY",
    "quantity": 2.0,
    "side": "BUY",
    "source": "MANAGED_CORE_LIVE_DRAFT",
    "status": "DRAFT_READY_FOR_REVIEW",
    "strategy_class": "DAILY_OR_MULTI_DAY_MOMENTUM",
    "t212_instrument_id": "INTC_US_EQ",
    "updated_at_utc": "2026-06-02T15:14:47+00:00"
  },
  "payload_hash_sha256": "c015f7b817a529d490998bda390b4fa62fc2fc4361c263bdfefa19ebeb077c18",
  "profile": "T212_PROFILE_CONFIRMED_EXECUTION",
  "status": "SUBMISSION_IN_PROGRESS",
  "token_id": "01e22493-9bc0-427e-a2f0-4c5118a7ba3a",
  "token_secret_hash": "4bbb756d5f888d8c5805cb2bf51b1b7c35e387a6e3326fa23e21185fb29bff33",
  "used": true
}
